cinesdk/__init__.py
cinesdk/film_client.py
cinesdk/film_config.py
cinesdk/schemas/__init__.py
cinesdk/schemas/schemas.py
cinesdk-0.0.2.dist-info/METADATA
cinesdk-0.0.2.dist-info/WHEEL
cinesdk-0.0.2.dist-info/top_level.txt
cinesdk-0.0.2.dist-info/RECORD
