Metadata-Version: 2.4
Name: cinesdk
Version: 0.0.2
Summary: Software Development Kit (SDK) for MovieLens API
Author: [Abdoul karim]
Classifier: Development Status :: 3 - Alpha
Classifier: Programming Language :: Python :: 3
Classifier: License :: OSI Approved :: MIT License
Classifier: Operating System :: OS Independent
Requires-Python: >=3.12
Requires-Dist: httpx>=0.28.1
Requires-Dist: pydantic>=2.11.4
Requires-Dist: backoff>=2.2.1
Requires-Dist: pandas>=2.2.3
Requires-Dist: numpy>=2.2.4
Requires-Dist: python-dotenv
